.coveragerc
AUTHORS
CONTRIBUTING.rst
LICENSE
MANIFEST.in
README.md
requirements.txt
setup.py
vxtwitter/__init__.py
vxtwitter/twitter.py
vxtwitter.egg-info/PKG-INFO
vxtwitter.egg-info/SOURCES.txt
vxtwitter.egg-info/dependency_links.txt
vxtwitter.egg-info/requires.txt
vxtwitter.egg-info/top_level.txt
vxtwitter/tests/__init__.py
vxtwitter/tests/test_twitter.py